combinemols3d/CombineMols3D.py
combinemols3d/__init__.py
combinemols3d-1.1.0.dist-info/LICENSE.txt
combinemols3d-1.1.0.dist-info/METADATA
combinemols3d-1.1.0.dist-info/WHEEL
combinemols3d-1.1.0.dist-info/top_level.txt
combinemols3d-1.1.0.dist-info/RECORD
