Metadata-Version: 2.1
Name: combinemols3d
Version: 1.1.0
Summary: Combine 2 molecules in 3D by sample.
Home-page: https://github.com/franklalalala/CombineMols3D
Author: Franklalalala
Author-email: franklalalala <1660810667@qq.com>
License: The MIT License (MIT)
Project-URL: Source, https://github.com/franklalalala/CombineMols3D
Platform: any
Classifier: Programming Language :: Python
Classifier: Intended Audience :: Science/Research
Classifier: License :: OSI Approved :: MIT License
Classifier: Natural Language :: English
Classifier: Development Status :: 3 - Alpha
Requires-Python: >=3.8
License-File: LICENSE.txt
Requires-Dist: importlib-metadata
Requires-Dist: ase
Requires-Dist: numpy
Requires-Dist: scipy
